{
  "분석 시작 시간": "2025-05-26 18:58:46",
  "분석 종료 시간": "2025-05-26 18:59:13",
  "총 프레임 수": 47,
  "감지된 얼굴 수": 60,
  "평균 감정 점수": 55.47742154010436,
  "최종 등급": "C-",
  "감정 분포": {
    "기쁨": {
      "횟수": 15,
      "비율": "24.6%",
      "평균 점수": "66.4",
      "최고 점수": "83.0",
      "최저 점수": "51.7"
    },
    "당황": {
      "횟수": 8,
      "비율": "13.1%",
      "평균 점수": "51.5",
      "최고 점수": "58.5",
      "최저 점수": "47.0"
    },
    "분노": {
      "횟수": 6,
      "비율": "9.8%",
      "평균 점수": "44.4",
      "최고 점수": "51.2",
      "최저 점수": "38.9"
    },
    "불안": {
      "횟수": 10,
      "비율": "16.4%",
      "평균 점수": "48.1",
      "최고 점수": "59.9",
      "최저 점수": "38.7"
    },
    "상처": {
      "횟수": 4,
      "비율": "6.6%",
      "평균 점수": "43.3",
      "최고 점수": "54.9",
      "최저 점수": "36.2"
    },
    "슬픔": {
      "횟수": 4,
      "비율": "6.6%",
      "평균 점수": "47.9",
      "최고 점수": "52.4",
      "최저 점수": "42.9"
    },
    "중립": {
      "횟수": 14,
      "비율": "23.0%",
      "평균 점수": "62.9",
      "최고 점수": "69.9",
      "최저 점수": "49.7"
    }
  }
}